odoo8_addon_l10n_ch_states-8.0.1.0.0.99.dev11-nspkg.pth
odoo_addons/l10n_ch_states/README.rst
odoo_addons/l10n_ch_states/__init__.py
odoo_addons/l10n_ch_states/__openerp__.py
odoo_addons/l10n_ch_states/data/res_country_states.xml
odoo_addons/l10n_ch_states/i18n/de.po
odoo_addons/l10n_ch_states/i18n/fr.po
odoo_addons/l10n_ch_states/i18n/fr_CH.po
odoo_addons/l10n_ch_states/i18n/it.po
odoo_addons/l10n_ch_states/i18n/l10n_ch_states.pot
odoo_addons/l10n_ch_states/i18n/nl_NL.po
odoo_addons/l10n_ch_states/i18n/sl.po
odoo_addons/l10n_ch_states/models/__init__.py
odoo_addons/l10n_ch_states/models/res_country.py
odoo_addons/l10n_ch_states/static/description/icon.png
odoo8_addon_l10n_ch_states-8.0.1.0.0.99.dev11.dist-info/METADATA
odoo8_addon_l10n_ch_states-8.0.1.0.0.99.dev11.dist-info/WHEEL
odoo8_addon_l10n_ch_states-8.0.1.0.0.99.dev11.dist-info/namespace_packages.txt
odoo8_addon_l10n_ch_states-8.0.1.0.0.99.dev11.dist-info/top_level.txt
odoo8_addon_l10n_ch_states-8.0.1.0.0.99.dev11.dist-info/RECORD
